asgivalid-0.5.7.dist-info/METADATA
asgivalid-0.5.7.dist-info/WHEEL
asgivalid-0.5.7.dist-info/licenses/LICENSE
asgivalid/__init__.py
asgivalid/asgivalid.cp310-win_amd64.pyd
asgivalid-0.5.7.dist-info/RECORD
